{
    "cancer_type": "Vaginal Cancer",
    "title": "Vaginal Cancer—Patient Version",
    "url": "https://www.cancer.gov/types/vaginal",
    "content": [
        {
            "section": "Paragraph",
            "text": "Infection with human papillomavirus (HPV) causes two-thirds of the cases of vaginal cancer. Vaccines that protect against infection with HPV may reduce the risk of vaginal cancer. When found early, vaginal cancer can often be cured. Explore the links on this page to learn more about vaginal cancer treatment, research, and clinical trials."
        },
        {
            "section": "Paragraph",
            "text": "NCI does not have PDQ evidence-based information about prevention of vaginal cancer."
        },
        {
            "section": "Paragraph",
            "text": "NCI does not have PDQ evidence-based information about screening for vaginal cancer."
        },
        {
            "section": "Paragraph",
            "text": "The information in this section is meant to help you cope with the many issues and concerns that occur when you have cancer."
        },
        {
            "section": "Paragraph",
            "text": "Gardasil 9 Vaccine Protects against Additional HPV Types"
        },
        {
            "section": "Paragraph",
            "text": "National Cancer Institute\nat the National Institutes of Health"
        }
    ],
    "related_links": [],
    "related_pages": {}
}